tkblock/__init__.py
tkblock/block_framebase.py
tkblock/block_framework.py
tkblock/block_service.py
tkblock/block_util.py
tkblock/block_waiting_screen.py
tkblock/canvas.py
tkblock/layout.py
tkblock/logger.py
tkblock/scrollbar.py
tkblock/thread_stop.py
tkblock/traceback.py
tkblock-2.4.1.dist-info/LICENSE
tkblock-2.4.1.dist-info/METADATA
tkblock-2.4.1.dist-info/WHEEL
tkblock-2.4.1.dist-info/top_level.txt
tkblock-2.4.1.dist-info/RECORD
