Metadata-Version: 2.1
Name: tkblock
Version: 2.4.1
Summary: tkinter block framework
Home-page: https://github.com/kuri-pome/tkblock
Author: kuri_pome
License: MIT
Keywords: tkinter place widget easy
Platform: UNKNOWN
Classifier: Programming Language :: Python :: 3.10
Classifier: Programming Language :: Python :: 3.11
License-File: LICENSE
